sort_images_exif.py
sort_images_exif-0.2.dist-info/entry_points.txt
sort_images_exif-0.2.dist-info/LICENSE
sort_images_exif-0.2.dist-info/WHEEL
sort_images_exif-0.2.dist-info/METADATA
sort_images_exif-0.2.dist-info/RECORD
